qtics/__init__.py
qtics/experiment.py
qtics/instruments/__init__.py
qtics/instruments/instrument.py
qtics/instruments/network/NA_N9916A.py
qtics/instruments/network/RS_SMA100B.py
qtics/instruments/network/proteox/__init__.py
qtics/instruments/network/proteox/instrument_session.py
qtics/instruments/network/proteox/proteox.py
qtics/instruments/network/proteox/uris.py
qtics/instruments/network/triton_ctrl.py
qtics/instruments/network_inst.py
qtics/instruments/niscope/pxie_5170r.py
qtics/instruments/serial/keithley2231a.py
qtics/instruments/serial/keithley6514.py
qtics/instruments/serial/rf_attenuator_3494_64/rf_attenuator_3494-64.ino
qtics/instruments/serial/rf_attenuator_3494_64/rf_attenuator_3494_64.py
qtics/instruments/serial/rf_switch_R591722600/rf_switch_R591722600.ino
qtics/instruments/serial/rf_switch_R591722600/rf_switch_R591722600.py
qtics/instruments/serial/synth_FSL0010.py
qtics/instruments/serial/voltage_source_SIM928.py
qtics/instruments/serial_inst.py
qtics/logger.py
qtics-0.0.5.dist-info/LICENSE
qtics-0.0.5.dist-info/METADATA
qtics-0.0.5.dist-info/WHEEL
qtics-0.0.5.dist-info/RECORD
