Metadata-Version: 2.3
Name: qtics
Version: 0.0.5
Summary: Quantum Technologies Instrumentation ControlS
License: Apache-2.0
Author: The BiQuTe Team
Requires-Python: >=3.11
Classifier: License :: OSI Approved :: Apache Software License
Classifier: Programming Language :: Python :: 3
Classifier: Programming Language :: Python :: 3.11
Classifier: Programming Language :: Python :: 3.12
Classifier: Programming Language :: Python :: 3.13
Classifier: Topic :: Scientific/Engineering :: Physics
Requires-Dist: autobahn (>=24.4.2,<25.0.0)
Requires-Dist: dotenv (>=0.9.9,<0.10.0)
Requires-Dist: niscope (>=1.4.6,<2.0.0)
Requires-Dist: numpy (>=1.24,<2.0)
Requires-Dist: pyserial (>=3.5,<4.0)
Project-URL: Repository, https://github.com/biqute/qtics/
